st_cytoscape/__init__.py
st_cytoscape/frontend/build/asset-manifest.json
st_cytoscape/frontend/build/bootstrap.min.css
st_cytoscape/frontend/build/index.html
st_cytoscape/frontend/build/static/js/main.6536736b.js
st_cytoscape/frontend/build/static/js/main.6536736b.js.LICENSE.txt
st_cytoscape/frontend/build/static/js/main.6536736b.js.map
st_verbose_cytoscape-0.0.7.dist-info/LICENSE
st_verbose_cytoscape-0.0.7.dist-info/METADATA
st_verbose_cytoscape-0.0.7.dist-info/WHEEL
st_verbose_cytoscape-0.0.7.dist-info/top_level.txt
st_verbose_cytoscape-0.0.7.dist-info/RECORD
