Metadata-Version: 2.1
Name: st-verbose-cytoscape
Version: 0.0.7
Summary: A Streamlit component to display a Cytoscape.js graph
Home-page: 
Author: 
Author-email: 
Requires-Python: >=3.6
License-File: LICENSE
Requires-Dist: streamlit>=0.63
